MANIFEST.in
README.md
setup.py
pymathis/Mathis_Objects.py
pymathis/__init__.py
pymathis/getDefaultMathisVal.py
pymathis/pymathis.py
pymathis/smartmathis.dll
pymathis/smartmathis.so
pymathis.egg-info/PKG-INFO
pymathis.egg-info/SOURCES.txt
pymathis.egg-info/dependency_links.txt
pymathis.egg-info/requires.txt
pymathis.egg-info/top_level.txt
pymathis/examples/Example_for_Parametric_Runs.py
pymathis/examples/Example_for_Standalone_Runs.py
pymathis/examples/Example_from_previous_Case.py
pymathis/tests/ProbeAndCtrlTEST.data
pymathis/tests/ProbeAndCtrlTEST.pickle
pymathis/tests/Test_Cas2.py
pymathis/tests/__init__.py
pymathis/tests/runStressTest.py
pymathis/tests/test_interface_mathis.py