Metadata-Version: 2.1
Name: pymathis
Version: 0.3.4
Summary: A library of interacting function to enable exchanges between MATHIS and python at each time steps
Home-page: https://gitlab.com/CSTB/pymathis
Author: Xavier FAURE, Francois DEMOUGE
Author-email: xavier.faure@cstb.fr, francois.demouge@cstb.fr
License: GNU Lesser General Public License
Platform: UNKNOWN
Classifier: License :: OSI Approved :: GNU General Public License v3 or later (GPLv3+)
Classifier: Programming Language :: Python :: 3
